{
    "movie": [
      {
        "id": "0000",
        "title": "Joker",
        "date_release": "2019-10-04",
        "image_path": "/udDclJoHjfjb8Ekgsd4FDteOkCU.jpg",
        "backdrop_path" : "/n6bUvigpRFqSwmPp1m2YADdbRBc.jpg",
        "popularity" : "534.771",
        "vote" : "8.5"
      },
      {
        "id": "0001",
        "title": "Terminator: Dark Fate",
        "date_release": "2019-11-01",
        "image_path": "/vqzNJRH4YyquRiWxCCOH0aXggHI.jpg",
        "backdrop_path" : "/a6cDxdwaQIFjSkXf7uskg78ZyTq.jpg",
        "popularity" : "374.6",
        "vote" : "6.6"
      },
      {
        "id": "0002",
        "title": "Maleficent: Mistress of Evil",
        "date_release": "2019-10-18",
        "image_path": "/tBuabjEqxzoUBHfbyNbd8ulgy5j.jpg",
        "backdrop_path" : "/skvI4rYFrKXS73BJxWGH54Omlvv.jpg",
        "popularity" : "214.876",
        "vote" : "7.2"
      },
      {
        "id": "0003",
        "title": "Cars",
        "date_release": "2006-06-09",
        "image_path": "/jpfkzbIXgKZqCZAkEkFH2VYF63s.jpg",
        "backdrop_path" : "/a1MlbLBk5Sy6YvMbSuKfwGlDVlb.jpg",
        "popularity" : "121.893",
        "vote" : "6.7"
      },
      {
        "id": "0004",
        "title": "El Camino: A Breaking Bad Movie",
        "date_release": "2019-10-11",
        "image_path": "/ePXuKdXZuJx8hHMNr2yM4jY2L7Z.jpg",
        "backdrop_path" : "/ijiE9WoGSwSzM16zTxvUneJ8RXc.jpg",
        "popularity" : "108.112",
        "vote" : "7.1"
      },
      {
        "id": "0005",
        "title": "47 Meters Down: Uncaged",
        "date_release": "2019-08-16",
        "image_path": "/g4z7mDmJmx23vsVg6XNWcnXb6gc.jpg",
        "backdrop_path" : "/3uG3aOhEzFCjcQulsJQiAzLSrw8.jpg",
        "popularity" : "107.197",
        "vote" : "5.1"
      },
      {
        "id": "0006",
        "title": "Zombieland: Double Tap",
        "date_release": "2019-10-18",
        "image_path": "/pIcV8XXIIvJCbtPoxF9qHMKdRr2.jpg",
        "backdrop_path" : "/jCCdt0e8Xe9ttvevD4S3TSMNdH.jpg",
        "popularity" : "106.325",
        "vote" : "7.4"
      },
      {
        "id": "0007",
        "title": "Good Boys",
        "date_release": "2019-08-16",
        "image_path": "/tximyCXMEnWIIyOy9STkOduUprG.jpg",
        "backdrop_path" : "/zIZv4pPJRg3YTnWWuotwXnYu1fM.jpg",
        "popularity" : "122.885",
        "vote" : "6.6"
      },
      {
        "id": "0008",
        "title": "The Lion King",
        "date_release": "2019-07-19",
        "image_path": "/2bXbqYdUdNVa8VIWXVfclP2ICtT.jpg",
        "backdrop_path" : "/nRXO2SnOA75OsWhNhXstHB8ZmI3.jpg",
        "popularity" : "139.524",
        "vote" : "7.1"
      },
      {
        "id": "0009",
        "title": "Ip Man 4: The Finale",
        "date_release": "2019-12-20",
        "image_path": "/vn94LlNrbUWIZZyAdmvUepFBeaY.jpg",
        "backdrop_path" : "/ekP6EVxL81lZ4ivcqPsoZ72rY0h.jpg",
        "popularity" : "92.996",
        "vote" : "0"
      }
    ]
  }